daily.py
daily-0.2.1.data/data/daily/client_sheets.json
daily-0.2.1.data/data/daily/template.txt
daily-0.2.1.dist-info/LICENSE
daily-0.2.1.dist-info/METADATA
daily-0.2.1.dist-info/WHEEL
daily-0.2.1.dist-info/entry_points.txt
daily-0.2.1.dist-info/top_level.txt
daily-0.2.1.dist-info/RECORD
