Metadata-Version: 2.1
Name: daily
Version: 0.2.1
Summary: Simple CLI tool to write on the #daily slack channel and its corresponding timesheet.
Home-page: https://github.com/antoniomdk/daily-celtiberian
Author: Antonio Molner Domenech
Author-email: antonio.molner@strivelabs.io
License: MIT
Keywords: daily,cli,timesheet
Platform: UNKNOWN
Classifier: Development Status :: 3 - Alpha
Classifier: Environment :: Console
Classifier: Intended Audience :: Developers
Classifier: Topic :: Software Development 
Classifier: License :: OSI Approved :: MIT License
Classifier: Programming Language :: Python :: 3
Classifier: Programming Language :: Python :: 3.4
Classifier: Programming Language :: Python :: 3.5
Classifier: Programming Language :: Python :: 3.6
Classifier: Programming Language :: Python :: 3.7
